{
  "selectFolder.title": "rassure-vscode: 作業フォルダの選択",
  "selectFolder.placeholder": "フォルダのパスを入力、または右のアイコンから選択してください",
  "selectFolder.tooltip": "フォルダを選択",
  "selectFolder.dialogTitle": "チケット保存フォルダを選択",
  "error.noFolder": "フォルダが開かれていません。VS Codeでフォルダを開くか、設定からチケット保存フォルダを指定してください。",
  "error.ticketNotFound": "チケット {0} が見つかりません",
  "export.fileFilter": "Excel ファイル",
  "export.dialogTitle": "エクスポート先を選択",
  "export.statusBar": "$(loading~spin) Rassure: Excel 出力中...",
  "export.success": "Rassure: {0} 件の課題を Excel にエクスポートしました → {1}",
  "export.error": "Rassure: Excel エクスポートに失敗しました — {0}",
  "board.title": "Rassure — ボード",
  "col.id": "ID",
  "col.status": "状況",
  "col.priority": "重要度",
  "col.target": "指摘対象",
  "col.category": "指摘種別",
  "col.description": "説明",
  "col.comments": "コメント",
  "col.reporter": "指摘者",
  "col.assignee": "担当者",
  "col.dueDate": "期限",
  "col.createdAt": "作成日",
  "col.updatedAt": "更新日",
  "worksheet.name": "課題一覧",
  "categories.default": "誤記\n記載不足\n要確認\n修正依頼\n質問",
  "error.openFile.noBasePath": "ファイルを開けません: ワークスペースまたは rassure.json の targetRoot が設定されていません。",
  "error.openFile.notFound": "ファイルが見つかりません。探索先: {0}"
}
